README.md
setup.cfg
setup.py
pyplotlm/__init__.py
pyplotlm/influence.py
pyplotlm/pyplotlm.py
pyplotlm/tools.py
pyplotlm.egg-info/PKG-INFO
pyplotlm.egg-info/SOURCES.txt
pyplotlm.egg-info/dependency_links.txt
pyplotlm.egg-info/requires.txt
pyplotlm.egg-info/top_level.txt