Metadata-Version: 2.1
Name: pyplotlm
Version: 0.1.4
Summary: A Python package for sklearn to produce linear regression summary and diagnostic plots similar to those made in R with summary.lm and plot.lm
Home-page: https://github.com/esmondhkchu/pyplotlm
Author: Esmond Chu
Author-email: chuhke@gmail.com
License: MIT
Download-URL: https://github.com/esmondhkchu/pyplotlm/archive/v0.1.4.tar.gz
Keywords: statistics,machine learning,regression
Platform: UNKNOWN
Classifier: Development Status :: 3 - Alpha
Classifier: Intended Audience :: Science/Research
Classifier: License :: OSI Approved :: MIT License
Classifier: Programming Language :: Python :: 3.6
Classifier: Programming Language :: Python :: 3.7
Classifier: Programming Language :: Python :: 3.8
